tmcm_lib/__init__.py
tmcm_lib/exceptions.py
tmcm_lib/module.py
tmcm_lib/motor.py
tmcm_lib/motor_union.py
tmcm_lib/port.py
tmcm_lib/switch.py
tmcm_lib/module_3110/module.py
tmcm_lib/module_3110/motor.py
TMCM_Lib-1.0.0.dist-info/LICENSE.txt
TMCM_Lib-1.0.0.dist-info/METADATA
TMCM_Lib-1.0.0.dist-info/WHEEL
TMCM_Lib-1.0.0.dist-info/top_level.txt
TMCM_Lib-1.0.0.dist-info/RECORD
