Metadata-Version: 2.1
Name: TMCM-Lib
Version: 1.0.0
Summary: Trinamic Motion Control Module Library for Python
Home-page: https://github.com/florian-lapp/tmcm-lib-py
Author: Florian Lapp
Author-email: e5abed0c@gmail.com
License: MIT
Keywords: Trinamic,TMCM,TMCL,Stepper-Motor-Control
Platform: UNKNOWN
Classifier: Development Status :: 5 - Production/Stable
Classifier: Intended Audience :: Developers
Classifier: Intended Audience :: Science/Research
Classifier: License :: OSI Approved :: MIT License
Classifier: Operating System :: OS Independent
Classifier: Typing :: Typed
Requires-Dist: pyserial
